LICENSE
README.md
pyproject.toml
clams_utils/__init__.py
clams_utils.egg-info/PKG-INFO
clams_utils.egg-info/SOURCES.txt
clams_utils.egg-info/dependency_links.txt
clams_utils.egg-info/entry_points.txt
clams_utils.egg-info/requires.txt
clams_utils.egg-info/top_level.txt
clams_utils/aapb/__init__.py
clams_utils/aapb/cli.py
clams_utils/aapb/converter_aapbjson.py
clams_utils/aapb/goldretriever.py
clams_utils/aapb/guidhandler.py
clams_utils/aapb/newshour_transcript_cleanup.py