Metadata-Version: 2.4
Name: clams-utils
Version: 251011
Summary: a collection of smaller helper/utility code of CLAMS platform
Author-email: Brandeis Lab for Linguistics and Computation <admin@clams.ai>
License-Expression: Apache-2.0
License-File: LICENSE
Requires-Dist: requests
Requires-Dist: lapps
Requires-Dist: mmif-python
Dynamic: license-file
